README.md
setup.py
rpiup/__init__.py
rpiup/__main__.py
rpiup/monitor.py
rpiup/os.py
rpiup/sd.py
rpiup/util.py
rpiup/varsfile.py
rpiup/wifi.py
rpiup.egg-info/PKG-INFO
rpiup.egg-info/SOURCES.txt
rpiup.egg-info/dependency_links.txt
rpiup.egg-info/entry_points.txt
rpiup.egg-info/requires.txt
rpiup.egg-info/top_level.txt
rpiup/boot-files/boot-utils.sh
rpiup/boot-files/firstboot.sh
rpiup/boot-files/resources/fstab
rpiup/boot-files/resources/network_interfaces
rpiup/boot-files/resources/setup.sh
rpiup/boot-files/resources/splash.png
rpiup/boot-files/resources/vars.sh
rpiup/boot-files/resources/docker/netswitch/config.yml
rpiup/boot-files/resources/docker/netswitch/docker-compose.yml
rpiup/templates/index.html