Metadata-Version: 2.1
Name: rpiup
Version: 0.0.8
Summary: UNKNOWN
Home-page: https://github.com/beasteers/rpiup
Author: Bea Steers
Author-email: bea.steers@gmail.com
License: BSD 3-Clause Clear License
Keywords: raspberrypi raspberry pi os firstboot setup boot partition install iot fleet
Platform: UNKNOWN
Provides-Extra: monitor
